robust_average/README.md
robust_average/__init__.py
robust_average/robust_average.py
robust_average-0.1.6.dist-info/METADATA
robust_average-0.1.6.dist-info/WHEEL
robust_average-0.1.6.dist-info/top_level.txt
robust_average-0.1.6.dist-info/RECORD
